odoo/addons/mail_cleanup/README.rst
odoo/addons/mail_cleanup/__init__.py
odoo/addons/mail_cleanup/__manifest__.py
odoo/addons/mail_cleanup/i18n/ca.po
odoo/addons/mail_cleanup/i18n/de.po
odoo/addons/mail_cleanup/i18n/es.po
odoo/addons/mail_cleanup/i18n/fr.po
odoo/addons/mail_cleanup/i18n/hr.po
odoo/addons/mail_cleanup/i18n/it.po
odoo/addons/mail_cleanup/i18n/mail_cleanup.pot
odoo/addons/mail_cleanup/i18n/pt_BR.po
odoo/addons/mail_cleanup/i18n/sl.po
odoo/addons/mail_cleanup/i18n/tr.po
odoo/addons/mail_cleanup/i18n/zh_CN.po
odoo/addons/mail_cleanup/models/__init__.py
odoo/addons/mail_cleanup/models/fetchmail_server.py
odoo/addons/mail_cleanup/readme/CONFIGURE.rst
odoo/addons/mail_cleanup/readme/CONTRIBUTORS.rst
odoo/addons/mail_cleanup/readme/DESCRIPTION.rst
odoo/addons/mail_cleanup/static/description/icon.png
odoo/addons/mail_cleanup/static/description/index.html
odoo/addons/mail_cleanup/views/mail_view.xml
odoo12_addon_mail_cleanup-12.0.1.0.0.99.dev4.dist-info/METADATA
odoo12_addon_mail_cleanup-12.0.1.0.0.99.dev4.dist-info/WHEEL
odoo12_addon_mail_cleanup-12.0.1.0.0.99.dev4.dist-info/top_level.txt
odoo12_addon_mail_cleanup-12.0.1.0.0.99.dev4.dist-info/RECORD
